{
  "label": "regionft_d8-GBDT-Adult-race-d5000000",
  "repeat": 0,
  "method": "regionft_d8",
  "model": "GBDT",
  "dataset": "Adult",
  "protected": "race",
  "runtime": 7200,
  "no_disc": 341956,
  "no_test": 5510152,
  "prec": 0.06205926805648919,
  "cpu_time": 188.367673459,
  "real_time": 188.377281665802,
  "partition": {
    "cpu_time": 34.52362083899999,
    "real_time": 34.52896475791931,
    "no_test": 510152,
    "no_disc": 18589,
    "n_regions": 231
  },
  "generation": {
    "cpu_time": 153.84405262,
    "real_time": 153.8483169078827,
    "no_test": 5000000,
    "no_disc": 323367
  },
  "config": {
    "max_depth": 8,
    "min_samples_per_region": 1000,
    "max_samples_per_region": 3000,
    "min_gain": 0.0,
    "gini_weight_mode": "sample",
    "max_split_ratio": 1.0,
    "sampling_risk_focus_alpha": 1.0,
    "sampling_risk_floor": 1e-05,
    "batch_size": 512,
    "disc_phase": "generation",
    "sample_draws": 5000000,
    "random_seed": 0
  }
}