{
  "label": "regionft_d6-DecTree-Credit-sex-d5000000",
  "repeat": 1,
  "method": "regionft_d6",
  "model": "DecTree",
  "dataset": "Credit",
  "protected": "sex",
  "runtime": 7200,
  "no_disc": 4218288,
  "no_test": 5058594,
  "prec": 0.8338854630357764,
  "cpu_time": 94.10253952,
  "real_time": 94.10329747200012,
  "partition": {
    "cpu_time": 3.685290020000025,
    "real_time": 3.6859896183013916,
    "no_test": 58594,
    "no_disc": 10928,
    "n_regions": 22
  },
  "generation": {
    "cpu_time": 90.41724949999997,
    "real_time": 90.41730785369873,
    "no_test": 5000000,
    "no_disc": 4207360
  },
  "config": {
    "max_depth": 6,
    "min_samples_per_region": 1000,
    "max_samples_per_region": 3000,
    "min_gain": 0.0,
    "gini_weight_mode": "sample",
    "max_split_ratio": 1.0,
    "sampling_risk_focus_alpha": 1.0,
    "sampling_risk_floor": 1e-05,
    "batch_size": 512,
    "disc_phase": "generation",
    "sample_draws": 5000000,
    "random_seed": 1
  }
}